the_python_bay/__init__.py
the_python_bay/main.py
the_python_bay/tests/__init__.py
the_python_bay/tests/test_the_python_bay.py
the_python_bay-1.2.3.dist-info/WHEEL
the_python_bay-1.2.3.dist-info/METADATA
the_python_bay-1.2.3.dist-info/RECORD
