Metadata-Version: 2.1
Name: the-python-bay
Version: 1.2.3
Summary: A python library for searching thepiratebay.org
Home-page: https://github.com/philhabell/the-python-bay
License: GNU General Public License
Author: Philip Bell
Author-email: philhabell@gmail.com
Maintainer: Philip Bell
Maintainer-email: philhabell@gmail.com
Requires-Python: >=3.9,<4.0
Classifier: License :: Other/Proprietary License
Classifier: Programming Language :: Python :: 3
Classifier: Programming Language :: Python :: 3.9
Requires-Dist: requests
Project-URL: Documentation, https://github.com/philhabell/the-python-bay/blob/main/README.md
Project-URL: Repository, https://github.com/philhabell/the-python-bay
